graphexecutor/__init__.py
graphexecutor/app.py
graphexecutor/builder.py
graphexecutor/checker.py
graphexecutor/parser.py
graphexecutor/runner.py
graphexecutor/tests/test_app.py
graphexecutor-0.1.5.dist-info/METADATA
graphexecutor-0.1.5.dist-info/WHEEL
graphexecutor-0.1.5.dist-info/entry_points.txt
graphexecutor-0.1.5.dist-info/RECORD
